superjson/.DS_Store
superjson/__init__.py
superjson/_superjson.py
superjson/_version.py
superjson/comments.py
superjson/helper.py
superjson/warning.py
superjson/__pycache__/__init__.cpython-38.pyc
superjson/__pycache__/_superjson.cpython-38.pyc
superjson/__pycache__/_version.cpython-38.pyc
superjson/__pycache__/comments.cpython-38.pyc
superjson/__pycache__/helper.cpython-38.pyc
superjson/__pycache__/warning.cpython-38.pyc
superjson/docs/__init__.py
superjson/docs/__pycache__/__init__.cpython-38.pyc
superjson/pkg/__init__.py
superjson/pkg/atomicwrites.py
superjson/pkg/compresslib.py
superjson/pkg/__pycache__/__init__.cpython-38.pyc
superjson/pkg/__pycache__/atomicwrites.cpython-38.pyc
superjson/pkg/__pycache__/compresslib.cpython-38.pyc
superjson-1.0.2.dist-info/AUTHORS.rst
superjson-1.0.2.dist-info/LICENSE.txt
superjson-1.0.2.dist-info/METADATA
superjson-1.0.2.dist-info/WHEEL
superjson-1.0.2.dist-info/top_level.txt
superjson-1.0.2.dist-info/RECORD
