Metadata-Version: 2.1
Name: superjson
Version: 1.0.2
Summary: Extendable json encode/decode library.
Home-page: https://github.com/MacHu-GWU/superjson-project
Author: Sanhe Hu
Author-email: husanhe@gmail.com
Maintainer: Sanhe Hu
Maintainer-email: husanhe@gmail.com
License: MIT
Download-URL: https://pypi.python.org/pypi/superjson/1.0.2#downloads
Platform: Windows
Platform: MacOS
Platform: Unix
Classifier: Development Status :: 5 - Production/Stable
Classifier: Intended Audience :: Developers
Classifier: License :: OSI Approved :: MIT License
Classifier: Natural Language :: English
Classifier: Operating System :: Microsoft :: Windows
Classifier: Operating System :: MacOS
Classifier: Operating System :: Unix
Classifier: Programming Language :: Python
Classifier: Programming Language :: Python :: 3 :: Only
Classifier: Programming Language :: Python :: 3.6
Classifier: Programming Language :: Python :: 3.7
Classifier: Programming Language :: Python :: 3.8
Classifier: Programming Language :: Python :: 3.9
License-File: LICENSE.txt
License-File: AUTHORS.rst
Provides-Extra: docs
Requires-Dist: sphinx (==3.5.4) ; extra == 'docs'
Requires-Dist: furo (==2021.6.18b36) ; extra == 'docs'
Requires-Dist: sphinx-inline-tabs (==2021.3.28b7) ; extra == 'docs'
Requires-Dist: sphinx-jinja (==1.1.0) ; extra == 'docs'
Requires-Dist: sphinx-copybutton (==0.2.5) ; extra == 'docs'
Requires-Dist: docfly (==0.0.18) ; extra == 'docs'
Requires-Dist: rstobj (==0.0.7) ; extra == 'docs'
Requires-Dist: Pygments (==2.9.0) ; extra == 'docs'
Provides-Extra: tests
Requires-Dist: pytest ; extra == 'tests'
Requires-Dist: pytest-cov ; extra == 'tests'
Requires-Dist: python-dateutil ; extra == 'tests'
